setup.py
NoseXML.egg-info/PKG-INFO
NoseXML.egg-info/SOURCES.txt
NoseXML.egg-info/entry_points.txt
NoseXML.egg-info/top_level.txt
nosexml/__init__.py
nosexml/plugin.py
