Metadata-Version: 1.0
Name: NoseXML
Version: 0.16
Summary: Nose XML Output plugin
Home-page: UNKNOWN
Author: Richard Clark
Author-email: richard@onesquared.net
License: UNKNOWN
Platform: UNKNOWN
Classifier: Development Status :: 3 - Alpha
Classifier: Intended Audience :: Developers
Classifier: Programming Language :: Python
Classifier: Topic :: Communications :: Email
Classifier: Topic :: Office/Business
Classifier: Topic :: Software Development :: Testing
